README.md
setup.py
meta_json_downloader/MetaFileDownloader.py
meta_json_downloader/__init__.py
meta_json_downloader.egg-info/PKG-INFO
meta_json_downloader.egg-info/SOURCES.txt
meta_json_downloader.egg-info/dependency_links.txt
meta_json_downloader.egg-info/requires.txt
meta_json_downloader.egg-info/top_level.txt
meta_json_downloader.egg-info/zip-safe