Metadata-Version: 2.1
Name: meta-json-downloader
Version: 0.1.0
Summary: A simple library example to download meta files from the meta_json_files repo
Home-page: https://gitlab.oceantrack.org/ceotr/practice_lab/meta-json-downloader-example
Author: CEOTR
Author-email: support@ceotr.ca
License: GNU General Public License v3 (GPLv3)
Platform: UNKNOWN
